gpac/__init__.py
gpac/crn.py
gpac/ode.py
gpac-1.1.9.dist-info/licenses/LICENSE
gpac-1.1.9.dist-info/METADATA
gpac-1.1.9.dist-info/WHEEL
gpac-1.1.9.dist-info/top_level.txt
gpac-1.1.9.dist-info/RECORD
