Metadata-Version: 2.4
Name: gpac
Version: 1.1.9
Summary: A Python package for plotting differential equation trajectories, and dealing with chemical reaction networks.
Home-page: https://github.com/UC-Davis-molecular-computing/gpac
Author: David Doty
Author-email: Dave Doty <doty@ucdavis.edu>
License: MIT
Project-URL: Homepage, https://github.com/UC-Davis-molecular-computing/gpac
Project-URL: Issues, https://github.com/UC-Davis-molecular-computing/gpac/issues
Project-URL: API, https://gpac.readthedocs.io/
Requires-Python: >=3.7
License-File: LICENSE
Requires-Dist: scipy>=1
Requires-Dist: sympy>=1
Requires-Dist: numpy>=2
Requires-Dist: matplotlib>=3
Requires-Dist: rebop>=0.9
Requires-Dist: xarray>=2025
Requires-Dist: tqdm>=4
Requires-Dist: polars>=1
Requires-Dist: ipywidgets>=8
Requires-Dist: ipykernel>=6
Requires-Dist: editdistance>=0.8
Provides-Extra: docs
Requires-Dist: mkdocs>=1.4.0; extra == "docs"
Requires-Dist: mkdocstrings[python]>=0.20.0; extra == "docs"
Requires-Dist: mkdocs-material>=9.1.0; extra == "docs"
Requires-Dist: pymdown-extensions; extra == "docs"
Provides-Extra: dev
Requires-Dist: black; extra == "dev"
Dynamic: author
Dynamic: home-page
Dynamic: license-file
Dynamic: requires-python
